jdl.cpython-36m-darwin.so
jpy-0.10.0-SNAPSHOT.jar
jpy.cpython-36m-darwin.so
jpyutil.py
deephaven_jpy-1.20211129.153.dist-info/LICENSE.txt
deephaven_jpy-1.20211129.153.dist-info/METADATA
deephaven_jpy-1.20211129.153.dist-info/WHEEL
deephaven_jpy-1.20211129.153.dist-info/top_level.txt
deephaven_jpy-1.20211129.153.dist-info/RECORD
