Metadata-Version: 2.1
Name: deephaven-jpy
Version: 1.20211129.153
Summary: Deephaven fork of jpy Bi-directional Python-Java bridge
Home-page: https://github.com/bcdev/jpy
Author: Deephaven Data Labs
Author-email: python@deephaven.io
Maintainer: Deephaven Data Labs
Maintainer-email: python@deephaven.io
License: Apache 2.0
Download-URL: https://pypi.python.org/pypi/jpy/1.20211129.153
Platform: Windows
Platform: Linux
Platform: Darwin
Classifier: Development Status :: 4 - Beta
Classifier: Intended Audience :: Developers
Classifier: License :: OSI Approved :: Apache Software License
Classifier: Programming Language :: Python :: 2
Classifier: Programming Language :: Python :: 2.7
Classifier: Programming Language :: Python :: 3
Classifier: Programming Language :: Python :: 3.5
Classifier: Programming Language :: Python :: 3.6
Classifier: Programming Language :: Python :: 3.7
